<?xml version="1.0" encoding="UTF-8" standalone="no"?><users>
  <user>
    <username>john_doe</username>
    <password>password123</password>
    <wallets>
    </wallets>
  </user>
  <user>
    <username>jane_doe</username>
    <password>password456</password>
    <wallets>
    </wallets>
  </user>
<user><username>batman</username><password>bat</password><wallets><wallet><name>UTC--2024-04-11T23-37-48.367335000Z--862eff1f5772b4bc7645a11a08d58a1df6d0549a.json</name><password>diowicocioj</password></wallet><wallet><name>UTC--2024-04-11T23-40-09.892441000Z--ea2d2e276033772f09311e0ce64dde5f2f329c17.json</name><password>fun</password></wallet><wallet><name>UTC--2024-04-12T00-37-40.547468000Z--9ab16a70cdfdfc5c07c0bd27f93fd021d3eac75e.json</name><password>fun</password></wallet><wallet><name>UTC--2024-04-12T00-37-42.612484000Z--61bc3679c6295c50867ad1e86dd14d07fba3d616.json</name><password>fun</password></wallet><wallet><name>UTC--2024-04-12T00-39-05.835230000Z--f11f5b6f456557cd3b224b3e0bec884f3c80810a.json</name><password>fun</password></wallet><wallet><name>UTC--2024-04-12T00-39-07.823740000Z--0c1dc01c63d78cac20ef54eb881ae6e440dd3d31.json</name><password>fun</password></wallet><wallet><name>UTC--2024-04-12T17-49-35.90899000Z--aeaf0d1abcf1874e5f30ec7e73501bae1eb8bb10.json</name><password>tree</password></wallet><wallet><name>UTC--2024-04-12T18-08-06.618231000Z--de149197fa21e39e9b3fa63bdcee5e29bb74a3bc.json</name><password>fun</password></wallet><wallet><name>UTC--2024-04-12T18-08-08.563856000Z--84aa04b6a6994360cb5bc02fa93cd541921bdc49.json</name><password>fun</password></wallet></wallets></user><user><username>Spencer</username><password>coding</password><wallets><wallet><name>UTC--2024-04-12T00-59-13.429779000Z--35f3a2ca458fd0258c023aa16f999e926c39d73e.json</name><password>coding</password></wallet></wallets></user><user><username>man</username><password>woman</password><wallets><wallet><name>UTC--2024-04-12T18-25-38.897038000Z--194ea450a939b635c2b18cb9acefef5caab988ab.json</name><password>stuff</password></wallet></wallets></user></users>